jack_netbridge/__init__.py
jack_netbridge/jack_netbridge.py
jack_netbridge/lib.py
jack_netbridge-0.2.0.dist-info/LICENSE
jack_netbridge-0.2.0.dist-info/METADATA
jack_netbridge-0.2.0.dist-info/WHEEL
jack_netbridge-0.2.0.dist-info/entry_points.txt
jack_netbridge-0.2.0.dist-info/RECORD
