Metadata-Version: 2.1
Name: jack-netbridge
Version: 0.2.0
Summary: Send and receive Jack MIDI data as multicast streams over network.
License: GNU GPL v3
Author: omnitonal.com
Requires-Python: >=3.11,<4.0
Classifier: License :: Other/Proprietary License
Classifier: Programming Language :: Python :: 3
Classifier: Programming Language :: Python :: 3.11
Requires-Dist: JACK-Client (>=0.5.4,<0.6.0)
Requires-Dist: mido (>=1.3.0,<2.0.0)
Requires-Dist: numpy (>=1.26.0,<2.0.0)
Requires-Dist: toml (>=0.10.2,<0.11.0)
